{
  "mockBidRequest": {
    "id": "test-request-id",
    "imp": [
      {
        "id": "test-imp-id",
        "banner": {
          "format": [{"w": 728, "h": 90}]
        },
        "ext": {
          "bidder": {
            "siteId": "fake-site-id",
            "productId": "inview",
            "zoneId": "fake-zone-id"
          }
        }
      }
    ],
    "site": {}
  },

  "httpCalls": [
    {
      "expectedRequest": {
        "uri": "http://ssc.33across.com",
        "body": {
          "ext": {
            "ttx": {
              "caller": [
                {
                  "name": "Prebid-Server",
                  "version": "n/a"
                }
              ]
            }
          },
          "id": "test-request-id",
          "imp": [
            {
              "id":"test-imp-id",
              "banner": {
                "format": [{"w": 728, "h": 90}]
              },
              "ext": {
                "ttx": {
                  "prod": "inview",
                  "zoneid": "fake-zone-id"
                }
              }
            }
          ],
          "site": {}
        }
      },
      "mockResponse": {
        "status": 204
      }
    }
  ],
  "expectedBidResponses": []
}
