{
  "mockBidRequest": {
    "id": "some-request-id",
    "device": {
      "ua": "test-user-agent",
      "ipv6": "2001:db8:3333:4444:5555:6666:7777:8888",
      "language": "en",
      "dnt": 0
    },
    "tmax": 1000,
    "user": {
      "buyeruid": "awesome-user"
    },
    "site": {
      "page": "test.com",
      "publisher": {
        "id": "123456789"
      }
    },
    "imp": [
      {
        "id": "some-impression-id1",
        "tagid": "ogTAGID",
        "banner": {
          "w": 320,
          "h": 50
        },
        "ext": {
          "bidder": {
            "clientToken": "some-client-token",
            "placementId": "some-placement-id"
          }
        }
      },
      {
        "id": "some-impression-id2",
        "tagid": "ogTAGID",
        "banner": {
          "w": 320,
          "h": 50
        },
        "ext": {
          "bidder": {
            "clientToken": "some-client-token",
            "placementId": "some-placement-id"
          }
        }
      }
    ]
  },
  "httpCalls": [
    {
      "expectedRequest": {
        "headers": {
          "Accept": [
            "application/json"
          ],
          "Content-Type": [
            "application/json;charset=utf-8"
          ],
          "X-Fa-Pbs-Adapter-Version": [
            "1.0.0"
          ],
          "X-Forwarded-For": [
            "2001:db8:3333:4444:5555:6666:7777:8888"
          ],
          "X-Openrtb-Version": [
            "2.5"
          ]
        },
        "uri": "https://example.com/1/prebid/requests",
        "body": {
          "id": "some-request-id",
          "device": {
            "ua": "test-user-agent",
            "ipv6": "2001:db8:3333:4444:5555:6666:7777:8888",
            "language": "en",
            "dnt": 0
          },
          "imp": [
            {
              "id": "some-impression-id1",
              "tagid": "ogTAGID",
              "banner": {
                "w": 320,
                "h": 50
              },
              "ext": {
                "bidder": {
                  "clientToken": "some-client-token",
                  "placementId": "some-placement-id"
                }
              }
            },
            {
              "id": "some-impression-id2",
              "tagid": "ogTAGID",
              "banner": {
                "w": 320,
                "h": 50
              },
              "ext": {
                "bidder": {
                  "clientToken": "some-client-token",
                  "placementId": "some-placement-id"
                }
              }
            }
          ],
          "site": {
            "page": "test.com",
            "publisher": {
              "id": "123456789"
            }
          },
          "user": {
            "buyeruid": "awesome-user"
          },
          "tmax": 1000
        },
        "impIDs": [
          "some-impression-id1",
          "some-impression-id2"
        ]
      },
      "mockResponse": {
        "status": 200,
        "body": {
          "id": "awesome-resp-id",
          "seatbid": [
            {
              "bid": [
                {
                  "id": "a3ae1b4e2fc24a4fb45540082e98e161",
                  "impid": "some-impression-id1",
                  "price": 3.5,
                  "adm": "awesome-markup",
                  "adomain": [
                    "awesome.com"
                  ],
                  "crid": "20",
                  "w": 320,
                  "h": 50,
                  "mtype": 1
                },
                {
                  "id": "a3ae1b4e2fc24a4fb45540082e98e162",
                  "impid": "some-impression-id2",
                  "price": 3.5,
                  "adm": "awesome-markup",
                  "adomain": [
                    "awesome.com"
                  ],
                  "crid": "20",
                  "w": 320,
                  "h": 50,
                  "mtype": 1
                }
              ],
              "type": "banner",
              "seat": "escalax"
            }
          ],
          "cur": "USD"
        }
      }
    }
  ],
  "expectedBidResponses": [
    {
      "bids": [
        {
          "bid": {
            "id": "a3ae1b4e2fc24a4fb45540082e98e161",
            "impid": "some-impression-id1",
            "price": 3.5,
            "adm": "awesome-markup",
            "crid": "20",
            "adomain": [
              "awesome.com"
            ],
            "w": 320,
            "h": 50,
            "mtype": 1
          },
          "type": "banner"
        },
        {
          "bid": {
            "id": "a3ae1b4e2fc24a4fb45540082e98e162",
            "impid": "some-impression-id2",
            "price": 3.5,
            "adm": "awesome-markup",
            "crid": "20",
            "adomain": [
              "awesome.com"
            ],
            "w": 320,
            "h": 50,
            "mtype": 1
          },
          "type": "banner"
        }
      ]
    }
  ]
}